sofficehelpers/ooutils.py
sofficehelpers/ssconverter.py
sofficehelpers/__init__.py
sofficehelpers-0.2.1.dist-info/DESCRIPTION.rst
sofficehelpers-0.2.1.dist-info/entry_points.txt
sofficehelpers-0.2.1.dist-info/RECORD
sofficehelpers-0.2.1.dist-info/WHEEL
sofficehelpers-0.2.1.dist-info/top_level.txt
sofficehelpers-0.2.1.dist-info/metadata.json
sofficehelpers-0.2.1.dist-info/METADATA
