Metadata-Version: 2.0
Name: sofficehelpers
Version: 0.2.1
Summary: Helpers for LibreOffice integration with automated tools
Home-page: https://github.com/chintal/tendril-sofficehelpers
Author: Chintalagiri Shashank
Author-email: shashank@chintal.in
License: GNU LGPLv2.1+
Platform: UNKNOWN
Classifier: Development Status :: 4 - Beta
Classifier: License :: OSI Approved :: GNU Lesser General Public License v2 or later (LGPLv2+)
Classifier: Programming Language :: Python :: 3.4
Classifier: Intended Audience :: Information Technology
Classifier: Natural Language :: English
Classifier: Operating System :: OS Independent
Classifier: Topic :: Utilities
